djangohosting
