Metadata-Version: 1.0
Name: djangohosting-recipe
Version: 0.1.0a4
Summary: Buildout recipe for Djangohosting.ch
Home-page: http://code.google.com/p/djangohosting-recipe/
Author: Damien Lebrun
Author-email: dinoboff@hotmail.com
License: BSD
Platform: UNKNOWN
Classifier: Framework :: Buildout
Classifier: Framework :: Django
Classifier: Topic :: Software Development :: Build Tools
Classifier: Development Status :: 3 - Alpha
Classifier: License :: OSI Approved :: BSD License
Classifier: Operating System :: MacOS :: MacOS X
Classifier: Operating System :: Microsoft :: Windows
Classifier: Operating System :: POSIX
